LICENSE.txt
README.md
pyproject.toml
setup.py
fewrap/__init__.py
fewrap/analysis_setup.py
fewrap/connect.py
fewrap/decorators.py
fewrap/fem_entities.py
fewrap/geometry.py
fewrap/groups.py
fewrap/helpers.py
fewrap/loads_and_bcs.py
fewrap/meshing.py
fewrap/results.py
fewrap/setup_pyfemap.py
fewrap/view_options.py
fewrap.egg-info/PKG-INFO
fewrap.egg-info/SOURCES.txt
fewrap.egg-info/dependency_links.txt
fewrap.egg-info/top_level.txt